faucet_tool/__init__.py
faucet_tool/faucet_tool.py
faucet_tool/mylib.py
faucet_tool-0.1.dist-info/LICENSE
faucet_tool-0.1.dist-info/METADATA
faucet_tool-0.1.dist-info/WHEEL
faucet_tool-0.1.dist-info/top_level.txt
faucet_tool-0.1.dist-info/RECORD
